reter/__init__.py
reter/reter.py
reter/lib/__init__.py
reter/lib/cursor/__init__.py
reter/lib/cursor/cursor.py
reter/lib/errhandler/__init__.py
reter/lib/errhandler/handle.py
reter/lib/errhandler/errors/IllegalArgumentError.py
reter/lib/errhandler/errors/UnexpectedResult.py
reter/lib/errhandler/errors/__init__.py
reter/lib/event/__init__.py
reter/lib/event/handle.py
reter/lib/event/input/__init__.py
reter/lib/event/input/keyboard/__init__.py
reter/lib/event/input/keyboard/keyboard.py
reter/lib/event/input/map/__init__.py
reter/lib/event/input/map/keys.py
reter/lib/style/__init__.py
reter/lib/style/colour.py
reter/lib/style/indicator.py
reter/lib/terminal/__init__.py
reter/lib/terminal/screen.py
reter/lib/terminal/term.py
reter-1.0.8.dist-info/LICENSE
reter-1.0.8.dist-info/METADATA
reter-1.0.8.dist-info/WHEEL
reter-1.0.8.dist-info/top_level.txt
reter-1.0.8.dist-info/RECORD
