Metadata-Version: 2.1
Name: reter
Version: 1.0.8
Summary: A unix/posix terminal manipulation library for python3
Home-page: https://github.com/ZackeryRSmith/Reter
Author: Zackery Smith
Author-email: zackery.smith82307@gmail.com
License: GNU GPL-3.0
Platform: UNKNOWN
Classifier: License :: OSI Approved :: GNU General Public License v3 (GPLv3)
Classifier: Programming Language :: Python
Classifier: Programming Language :: Python :: 3
Classifier: Programming Language :: Python :: 3.6
Classifier: Programming Language :: Python :: 3.9
Classifier: Programming Language :: Python :: 3.10
Requires-Python: >=3.0.0
